{"config":{"output_file":null,"full_docs":false,"pub_only":true,"reachable_only":true,"distro_crate":false,"signatures":false,"borrow_data":false},"version":"0.19.1","compilation":{"directory":"/home/nick12345/.cargo/registry/src/github.com-1ecc6299db9ec823/gql_client-1.0.7","program":"/home/nick12345/.rustup/toolchains/stable-x86_64-unknown-linux-gnu/bin/rls","arguments":["--crate-name","gql_client","--edition=2018","/home/nick12345/.cargo/registry/src/github.com-1ecc6299db9ec823/gql_client-1.0.7/src/lib.rs","--json=diagnostic-rendered-ansi,artifacts,future-incompat","--crate-type","lib","--emit=dep-info,metadata","-C","embed-bitcode=no","-C","debuginfo=2","-C","metadata=90fe3b48c202fad0","-C","extra-filename=-90fe3b48c202fad0","--out-dir","/home/nick12345/Desktop/dir_git/dealtech_front/lightning/target/rls/debug/deps","-L","dependency=/home/nick12345/Desktop/dir_git/dealtech_front/lightning/target/rls/debug/deps","--extern","log=/home/nick12345/Desktop/dir_git/dealtech_front/lightning/target/rls/debug/deps/liblog-bda40c43492e48d6.rmeta","--extern","reqwest=/home/nick12345/Desktop/dir_git/dealtech_front/lightning/target/rls/debug/deps/libreqwest-0950b0b9edee94de.rmeta","--extern","serde=/home/nick12345/Desktop/dir_git/dealtech_front/lightning/target/rls/debug/deps/libserde-fe389d69affe6ed5.rmeta","--extern","serde_json=/home/nick12345/Desktop/dir_git/dealtech_front/lightning/target/rls/debug/deps/libserde_json-91476e35aab7df59.rmeta","--cap-lints","allow","--error-format=json","--sysroot","/home/nick12345/.rustup/toolchains/stable-x86_64-unknown-linux-gnu"],"output":"/home/nick12345/Desktop/dir_git/dealtech_front/lightning/target/rls/debug/deps/libgql_client-90fe3b48c202fad0.rmeta"},"prelude":{"crate_id":{"name":"gql_client","disambiguator":[4634064204704525139,0]},"crate_root":"/home/nick12345/.cargo/registry/src/github.com-1ecc6299db9ec823/gql_client-1.0.7/src","external_crates":[{"file_name":"/home/nick12345/.cargo/registry/src/github.com-1ecc6299db9ec823/gql_client-1.0.7/src/lib.rs","num":1,"id":{"name":"std","disambiguator":[9914303954752503396,0]}},{"file_name":"/home/nick12345/.cargo/registry/src/github.com-1ecc6299db9ec823/gql_client-1.0.7/src/lib.rs","num":2,"id":{"name":"core","disambiguator":[15846600599516386926,0]}},{"file_name":"/home/nick12345/.cargo/registry/src/github.com-1ecc6299db9ec823/gql_client-1.0.7/src/lib.rs","num":3,"id":{"name":"compiler_builtins","disambiguator":[3248197779922953368,0]}},{"file_name":"/home/nick12345/.cargo/registry/src/github.com-1ecc6299db9ec823/gql_client-1.0.7/src/lib.rs","num":4,"id":{"name":"rustc_std_workspace_core","disambiguator":[16106073209810206859,0]}},{"file_name":"/home/nick12345/.cargo/registry/src/github.com-1ecc6299db9ec823/gql_client-1.0.7/src/lib.rs","num":5,"id":{"name":"alloc","disambiguator":[705058097557950442,0]}},{"file_name":"/home/nick12345/.cargo/registry/src/github.com-1ecc6299db9ec823/gql_client-1.0.7/src/lib.rs","num":6,"id":{"name":"libc","disambiguator":[4226859831290989395,0]}},{"file_name":"/home/nick12345/.cargo/registry/src/github.com-1ecc6299db9ec823/gql_client-1.0.7/src/lib.rs","num":7,"id":{"name":"unwind","disambiguator":[8113236783331938933,0]}},{"file_name":"/home/nick12345/.cargo/registry/src/github.com-1ecc6299db9ec823/gql_client-1.0.7/src/lib.rs","num":8,"id":{"name":"cfg_if","disambiguator":[17166186933304791475,0]}},{"file_name":"/home/nick12345/.cargo/registry/src/github.com-1ecc6299db9ec823/gql_client-1.0.7/src/lib.rs","num":9,"id":{"name":"miniz_oxide","disambiguator":[9102879459332679527,0]}},{"file_name":"/home/nick12345/.cargo/registry/src/github.com-1ecc6299db9ec823/gql_client-1.0.7/src/lib.rs","num":10,"id":{"name":"rustc_std_workspace_alloc","disambiguator":[17334790913793278849,0]}},{"file_name":"/home/nick12345/.cargo/registry/src/github.com-1ecc6299db9ec823/gql_client-1.0.7/src/lib.rs","num":11,"id":{"name":"adler","disambiguator":[15832914008974928315,0]}},{"file_name":"/home/nick12345/.cargo/registry/src/github.com-1ecc6299db9ec823/gql_client-1.0.7/src/lib.rs","num":12,"id":{"name":"hashbrown","disambiguator":[4406420180649270496,0]}},{"file_name":"/home/nick12345/.cargo/registry/src/github.com-1ecc6299db9ec823/gql_client-1.0.7/src/lib.rs","num":13,"id":{"name":"std_detect","disambiguator":[1969707906566880681,0]}},{"file_name":"/home/nick12345/.cargo/registry/src/github.com-1ecc6299db9ec823/gql_client-1.0.7/src/lib.rs","num":14,"id":{"name":"rustc_demangle","disambiguator":[13786306822812891743,0]}},{"file_name":"/home/nick12345/.cargo/registry/src/github.com-1ecc6299db9ec823/gql_client-1.0.7/src/lib.rs","num":15,"id":{"name":"addr2line","disambiguator":[3136484058452542816,0]}},{"file_name":"/home/nick12345/.cargo/registry/src/github.com-1ecc6299db9ec823/gql_client-1.0.7/src/lib.rs","num":16,"id":{"name":"gimli","disambiguator":[4549596711944770628,0]}},{"file_name":"/home/nick12345/.cargo/registry/src/github.com-1ecc6299db9ec823/gql_client-1.0.7/src/lib.rs","num":17,"id":{"name":"object","disambiguator":[11754765901466761141,0]}},{"file_name":"/home/nick12345/.cargo/registry/src/github.com-1ecc6299db9ec823/gql_client-1.0.7/src/lib.rs","num":18,"id":{"name":"memchr","disambiguator":[12231018808310572442,0]}},{"file_name":"/home/nick12345/.cargo/registry/src/github.com-1ecc6299db9ec823/gql_client-1.0.7/src/lib.rs","num":19,"id":{"name":"panic_unwind","disambiguator":[12139228928510032792,0]}},{"file_name":"/home/nick12345/.cargo/registry/src/github.com-1ecc6299db9ec823/gql_client-1.0.7/src/client.rs","num":20,"id":{"name":"reqwest","disambiguator":[9390228157214598927,0]}},{"file_name":"/home/nick12345/.cargo/registry/src/github.com-1ecc6299db9ec823/gql_client-1.0.7/src/client.rs","num":21,"id":{"name":"http","disambiguator":[11333795193288566686,0]}},{"file_name":"/home/nick12345/.cargo/registry/src/github.com-1ecc6299db9ec823/gql_client-1.0.7/src/client.rs","num":22,"id":{"name":"fnv","disambiguator":[3388228504314371916,0]}},{"file_name":"/home/nick12345/.cargo/registry/src/github.com-1ecc6299db9ec823/gql_client-1.0.7/src/client.rs","num":23,"id":{"name":"bytes","disambiguator":[10438007896072012438,0]}},{"file_name":"/home/nick12345/.cargo/registry/src/github.com-1ecc6299db9ec823/gql_client-1.0.7/src/client.rs","num":24,"id":{"name":"itoa","disambiguator":[13318191299545705178,0]}},{"file_name":"/home/nick12345/.cargo/registry/src/github.com-1ecc6299db9ec823/gql_client-1.0.7/src/client.rs","num":25,"id":{"name":"url","disambiguator":[1433135829290964546,0]}},{"file_name":"/home/nick12345/.cargo/registry/src/github.com-1ecc6299db9ec823/gql_client-1.0.7/src/client.rs","num":26,"id":{"name":"form_urlencoded","disambiguator":[14401765580902448421,0]}},{"file_name":"/home/nick12345/.cargo/registry/src/github.com-1ecc6299db9ec823/gql_client-1.0.7/src/client.rs","num":27,"id":{"name":"percent_encoding","disambiguator":[14994067487341571851,0]}},{"file_name":"/home/nick12345/.cargo/registry/src/github.com-1ecc6299db9ec823/gql_client-1.0.7/src/client.rs","num":28,"id":{"name":"idna","disambiguator":[7534625718191199859,0]}},{"file_name":"/home/nick12345/.cargo/registry/src/github.com-1ecc6299db9ec823/gql_client-1.0.7/src/client.rs","num":29,"id":{"name":"unicode_bidi","disambiguator":[1432040579261456608,0]}},{"file_name":"/home/nick12345/.cargo/registry/src/github.com-1ecc6299db9ec823/gql_client-1.0.7/src/client.rs","num":30,"id":{"name":"unicode_normalization","disambiguator":[13019000416568985879,0]}},{"file_name":"/home/nick12345/.cargo/registry/src/github.com-1ecc6299db9ec823/gql_client-1.0.7/src/client.rs","num":31,"id":{"name":"tinyvec","disambiguator":[10446490025230279515,0]}},{"file_name":"/home/nick12345/.cargo/registry/src/github.com-1ecc6299db9ec823/gql_client-1.0.7/src/client.rs","num":32,"id":{"name":"tinyvec_macros","disambiguator":[11250283674178718717,0]}},{"file_name":"/home/nick12345/.cargo/registry/src/github.com-1ecc6299db9ec823/gql_client-1.0.7/src/client.rs","num":33,"id":{"name":"futures_core","disambiguator":[2889476389752248248,0]}},{"file_name":"/home/nick12345/.cargo/registry/src/github.com-1ecc6299db9ec823/gql_client-1.0.7/src/client.rs","num":34,"id":{"name":"log","disambiguator":[17988533960493539055,0]}},{"file_name":"/home/nick12345/.cargo/registry/src/github.com-1ecc6299db9ec823/gql_client-1.0.7/src/client.rs","num":35,"id":{"name":"cfg_if","disambiguator":[12105970879533839803,0]}},{"file_name":"/home/nick12345/.cargo/registry/src/github.com-1ecc6299db9ec823/gql_client-1.0.7/src/client.rs","num":36,"id":{"name":"http_body","disambiguator":[17532813671665367723,0]}},{"file_name":"/home/nick12345/.cargo/registry/src/github.com-1ecc6299db9ec823/gql_client-1.0.7/src/client.rs","num":37,"id":{"name":"pin_project_lite","disambiguator":[13349260882500549000,0]}},{"file_name":"/home/nick12345/.cargo/registry/src/github.com-1ecc6299db9ec823/gql_client-1.0.7/src/client.rs","num":38,"id":{"name":"tokio","disambiguator":[13577318567575450988,0]}},{"file_name":"/home/nick12345/.cargo/registry/src/github.com-1ecc6299db9ec823/gql_client-1.0.7/src/client.rs","num":39,"id":{"name":"mio","disambiguator":[9061626690516692730,0]}},{"file_name":"/home/nick12345/.cargo/registry/src/github.com-1ecc6299db9ec823/gql_client-1.0.7/src/client.rs","num":40,"id":{"name":"libc","disambiguator":[17435338370399650229,0]}},{"file_name":"/home/nick12345/.cargo/registry/src/github.com-1ecc6299db9ec823/gql_client-1.0.7/src/client.rs","num":41,"id":{"name":"memchr","disambiguator":[6978731604939472485,0]}},{"file_name":"/home/nick12345/.cargo/registry/src/github.com-1ecc6299db9ec823/gql_client-1.0.7/src/client.rs","num":42,"id":{"name":"socket2","disambiguator":[5536430469249517055,0]}},{"file_name":"/home/nick12345/.cargo/registry/src/github.com-1ecc6299db9ec823/gql_client-1.0.7/src/client.rs","num":43,"id":{"name":"futures_util","disambiguator":[17921343569299182158,0]}},{"file_name":"/home/nick12345/.cargo/registry/src/github.com-1ecc6299db9ec823/gql_client-1.0.7/src/client.rs","num":44,"id":{"name":"pin_utils","disambiguator":[14779779622709215863,0]}},{"file_name":"/home/nick12345/.cargo/registry/src/github.com-1ecc6299db9ec823/gql_client-1.0.7/src/client.rs","num":45,"id":{"name":"futures_macro","disambiguator":[6906675616549803926,0]}},{"file_name":"/home/nick12345/.cargo/registry/src/github.com-1ecc6299db9ec823/gql_client-1.0.7/src/client.rs","num":46,"id":{"name":"futures_task","disambiguator":[14504772446370623985,0]}},{"file_name":"/home/nick12345/.cargo/registry/src/github.com-1ecc6299db9ec823/gql_client-1.0.7/src/client.rs","num":47,"id":{"name":"futures_sink","disambiguator":[17069752836241684674,0]}},{"file_name":"/home/nick12345/.cargo/registry/src/github.com-1ecc6299db9ec823/gql_client-1.0.7/src/client.rs","num":48,"id":{"name":"futures_channel","disambiguator":[12723433582893712259,0]}},{"file_name":"/home/nick12345/.cargo/registry/src/github.com-1ecc6299db9ec823/gql_client-1.0.7/src/client.rs","num":49,"id":{"name":"slab","disambiguator":[8845407529126862251,0]}},{"file_name":"/home/nick12345/.cargo/registry/src/github.com-1ecc6299db9ec823/gql_client-1.0.7/src/client.rs","num":50,"id":{"name":"futures_io","disambiguator":[13768654741826238221,0]}},{"file_name":"/home/nick12345/.cargo/registry/src/github.com-1ecc6299db9ec823/gql_client-1.0.7/src/client.rs","num":51,"id":{"name":"hyper","disambiguator":[10259911340770936438,0]}},{"file_name":"/home/nick12345/.cargo/registry/src/github.com-1ecc6299db9ec823/gql_client-1.0.7/src/client.rs","num":52,"id":{"name":"tracing","disambiguator":[5595718392080354304,0]}},{"file_name":"/home/nick12345/.cargo/registry/src/github.com-1ecc6299db9ec823/gql_client-1.0.7/src/client.rs","num":53,"id":{"name":"tracing_core","disambiguator":[15038953675681300187,0]}},{"file_name":"/home/nick12345/.cargo/registry/src/github.com-1ecc6299db9ec823/gql_client-1.0.7/src/client.rs","num":54,"id":{"name":"once_cell","disambiguator":[15736546551684500465,0]}},{"file_name":"/home/nick12345/.cargo/registry/src/github.com-1ecc6299db9ec823/gql_client-1.0.7/src/client.rs","num":55,"id":{"name":"tracing_attributes","disambiguator":[509018045824147239,0]}},{"file_name":"/home/nick12345/.cargo/registry/src/github.com-1ecc6299db9ec823/gql_client-1.0.7/src/client.rs","num":56,"id":{"name":"tower_service","disambiguator":[15227278192046161533,0]}},{"file_name":"/home/nick12345/.cargo/registry/src/github.com-1ecc6299db9ec823/gql_client-1.0.7/src/client.rs","num":57,"id":{"name":"h2","disambiguator":[10926725661104536756,0]}},{"file_name":"/home/nick12345/.cargo/registry/src/github.com-1ecc6299db9ec823/gql_client-1.0.7/src/client.rs","num":58,"id":{"name":"tokio_util","disambiguator":[9415969570543894326,0]}},{"file_name":"/home/nick12345/.cargo/registry/src/github.com-1ecc6299db9ec823/gql_client-1.0.7/src/client.rs","num":59,"id":{"name":"indexmap","disambiguator":[9717016091760677484,0]}},{"file_name":"/home/nick12345/.cargo/registry/src/github.com-1ecc6299db9ec823/gql_client-1.0.7/src/client.rs","num":60,"id":{"name":"hashbrown","disambiguator":[17525588513902506349,0]}},{"file_name":"/home/nick12345/.cargo/registry/src/github.com-1ecc6299db9ec823/gql_client-1.0.7/src/client.rs","num":61,"id":{"name":"httparse","disambiguator":[5774478491591004260,0]}},{"file_name":"/home/nick12345/.cargo/registry/src/github.com-1ecc6299db9ec823/gql_client-1.0.7/src/client.rs","num":62,"id":{"name":"want","disambiguator":[2687079866978482641,0]}},{"file_name":"/home/nick12345/.cargo/registry/src/github.com-1ecc6299db9ec823/gql_client-1.0.7/src/client.rs","num":63,"id":{"name":"try_lock","disambiguator":[3756906096925167040,0]}},{"file_name":"/home/nick12345/.cargo/registry/src/github.com-1ecc6299db9ec823/gql_client-1.0.7/src/client.rs","num":64,"id":{"name":"native_tls","disambiguator":[15979117720688847517,0]}},{"file_name":"/home/nick12345/.cargo/registry/src/github.com-1ecc6299db9ec823/gql_client-1.0.7/src/client.rs","num":65,"id":{"name":"openssl","disambiguator":[16606295946946882242,0]}},{"file_name":"/home/nick12345/.cargo/registry/src/github.com-1ecc6299db9ec823/gql_client-1.0.7/src/client.rs","num":66,"id":{"name":"openssl_sys","disambiguator":[11883298902915651001,0]}},{"file_name":"/home/nick12345/.cargo/registry/src/github.com-1ecc6299db9ec823/gql_client-1.0.7/src/client.rs","num":67,"id":{"name":"foreign_types","disambiguator":[4052274091705878644,0]}},{"file_name":"/home/nick12345/.cargo/registry/src/github.com-1ecc6299db9ec823/gql_client-1.0.7/src/client.rs","num":68,"id":{"name":"foreign_types_shared","disambiguator":[4143028513284356272,0]}},{"file_name":"/home/nick12345/.cargo/registry/src/github.com-1ecc6299db9ec823/gql_client-1.0.7/src/client.rs","num":69,"id":{"name":"openssl_macros","disambiguator":[16001615550602259291,0]}},{"file_name":"/home/nick12345/.cargo/registry/src/github.com-1ecc6299db9ec823/gql_client-1.0.7/src/client.rs","num":70,"id":{"name":"bitflags","disambiguator":[9922722930592506933,0]}},{"file_name":"/home/nick12345/.cargo/registry/src/github.com-1ecc6299db9ec823/gql_client-1.0.7/src/client.rs","num":71,"id":{"name":"openssl_probe","disambiguator":[17177711402985819448,0]}},{"file_name":"/home/nick12345/.cargo/registry/src/github.com-1ecc6299db9ec823/gql_client-1.0.7/src/client.rs","num":72,"id":{"name":"base64","disambiguator":[6154480669114018360,0]}},{"file_name":"/home/nick12345/.cargo/registry/src/github.com-1ecc6299db9ec823/gql_client-1.0.7/src/client.rs","num":73,"id":{"name":"serde","disambiguator":[11820165331880733435,0]}},{"file_name":"/home/nick12345/.cargo/registry/src/github.com-1ecc6299db9ec823/gql_client-1.0.7/src/client.rs","num":74,"id":{"name":"serde_derive","disambiguator":[1107309963877279862,0]}},{"file_name":"/home/nick12345/.cargo/registry/src/github.com-1ecc6299db9ec823/gql_client-1.0.7/src/client.rs","num":75,"id":{"name":"serde_json","disambiguator":[17332270913172896087,0]}},{"file_name":"/home/nick12345/.cargo/registry/src/github.com-1ecc6299db9ec823/gql_client-1.0.7/src/client.rs","num":76,"id":{"name":"ryu","disambiguator":[1124649613102954550,0]}},{"file_name":"/home/nick12345/.cargo/registry/src/github.com-1ecc6299db9ec823/gql_client-1.0.7/src/client.rs","num":77,"id":{"name":"encoding_rs","disambiguator":[4895043858167752458,0]}},{"file_name":"/home/nick12345/.cargo/registry/src/github.com-1ecc6299db9ec823/gql_client-1.0.7/src/client.rs","num":78,"id":{"name":"mime","disambiguator":[15529236195606299558,0]}},{"file_name":"/home/nick12345/.cargo/registry/src/github.com-1ecc6299db9ec823/gql_client-1.0.7/src/client.rs","num":79,"id":{"name":"tokio_native_tls","disambiguator":[4803675332968080988,0]}},{"file_name":"/home/nick12345/.cargo/registry/src/github.com-1ecc6299db9ec823/gql_client-1.0.7/src/client.rs","num":80,"id":{"name":"ipnet","disambiguator":[6670897881766466269,0]}},{"file_name":"/home/nick12345/.cargo/registry/src/github.com-1ecc6299db9ec823/gql_client-1.0.7/src/client.rs","num":81,"id":{"name":"serde_urlencoded","disambiguator":[1994076303777144288,0]}},{"file_name":"/home/nick12345/.cargo/registry/src/github.com-1ecc6299db9ec823/gql_client-1.0.7/src/client.rs","num":82,"id":{"name":"hyper_tls","disambiguator":[10151418372230107573,0]}}],"span":{"file_name":"/home/nick12345/.cargo/registry/src/github.com-1ecc6299db9ec823/gql_client-1.0.7/src/lib.rs","byte_start":0,"byte_end":3318,"line_start":1,"line_end":134,"column_start":1,"column_end":18}},"imports":[{"kind":"Use","ref_id":{"krate":0,"index":147},"span":{"file_name":"/home/nick12345/.cargo/registry/src/github.com-1ecc6299db9ec823/gql_client-1.0.7/src/lib.rs","byte_start":3215,"byte_end":3224,"line_start":131,"line_end":131,"column_start":17,"column_end":26},"alias_span":null,"name":"Client","value":"","parent":{"krate":0,"index":0}},{"kind":"Use","ref_id":{"krate":0,"index":217},"span":{"file_name":"/home/nick12345/.cargo/registry/src/github.com-1ecc6299db9ec823/gql_client-1.0.7/src/lib.rs","byte_start":3251,"byte_end":3263,"line_start":132,"line_end":132,"column_start":16,"column_end":28},"alias_span":null,"name":"GraphQLError","value":"","parent":{"krate":0,"index":0}},{"kind":"Use","ref_id":{"krate":0,"index":222},"span":{"file_name":"/home/nick12345/.cargo/registry/src/github.com-1ecc6299db9ec823/gql_client-1.0.7/src/lib.rs","byte_start":3280,"byte_end":3299,"line_start":133,"line_end":133,"column_start":16,"column_end":35},"alias_span":null,"name":"GraphQLErrorMessage","value":"","parent":{"krate":0,"index":0}},{"kind":"GlobUse","ref_id":null,"span":{"file_name":"/home/nick12345/.cargo/registry/src/github.com-1ecc6299db9ec823/gql_client-1.0.7/src/lib.rs","byte_start":3316,"byte_end":3317,"line_start":134,"line_end":134,"column_start":16,"column_end":17},"alias_span":null,"name":"*","value":"ClientConfig","parent":{"krate":0,"index":0}}],"defs":[{"kind":"Mod","id":{"krate":0,"index":0},"span":{"file_name":"/home/nick12345/.cargo/registry/src/github.com-1ecc6299db9ec823/gql_client-1.0.7/src/lib.rs","byte_start":0,"byte_end":3318,"line_start":1,"line_end":134,"column_start":1,"column_end":18},"name":"","qualname":"::","value":"/home/nick12345/.cargo/registry/src/github.com-1ecc6299db9ec823/gql_client-1.0.7/src/lib.rs","parent":null,"children":[{"krate":0,"index":1},{"krate":0,"index":2},{"krate":0,"index":3},{"krate":0,"index":84},{"krate":0,"index":116},{"krate":0,"index":137},{"krate":0,"index":140},{"krate":0,"index":143},{"krate":0,"index":146}],"decl_id":null,"docs":" Minimal GraphQL client for rust","sig":null,"attributes":[{"value":"/ Minimal GraphQL client for rust","span":{"file_name":"/home/nick12345/.cargo/registry/src/github.com-1ecc6299db9ec823/gql_client-1.0.7/src/lib.rs","byte_start":39,"byte_end":74,"line_start":2,"line_end":2,"column_start":1,"column_end":36}},{"value":"/","span":{"file_name":"/home/nick12345/.cargo/registry/src/github.com-1ecc6299db9ec823/gql_client-1.0.7/src/lib.rs","byte_start":75,"byte_end":78,"line_start":3,"line_end":3,"column_start":1,"column_end":4}},{"value":"/ * Simple API, supports queries and mutations","span":{"file_name":"/home/nick12345/.cargo/registry/src/github.com-1ecc6299db9ec823/gql_client-1.0.7/src/lib.rs","byte_start":79,"byte_end":127,"line_start":4,"line_end":4,"column_start":1,"column_end":49}},{"value":"/ * Does not require schema file for introspection","span":{"file_name":"/home/nick12345/.cargo/registry/src/github.com-1ecc6299db9ec823/gql_client-1.0.7/src/lib.rs","byte_start":128,"byte_end":180,"line_start":5,"line_end":5,"column_start":1,"column_end":53}},{"value":"/ * Supports WebAssembly","span":{"file_name":"/home/nick12345/.cargo/registry/src/github.com-1ecc6299db9ec823/gql_client-1.0.7/src/lib.rs","byte_start":181,"byte_end":207,"line_start":6,"line_end":6,"column_start":1,"column_end":27}},{"value":"/","span":{"file_name":"/home/nick12345/.cargo/registry/src/github.com-1ecc6299db9ec823/gql_client-1.0.7/src/lib.rs","byte_start":208,"byte_end":211,"line_start":7,"line_end":7,"column_start":1,"column_end":4}},{"value":"/ # Basic Usage","span":{"file_name":"/home/nick12345/.cargo/registry/src/github.com-1ecc6299db9ec823/gql_client-1.0.7/src/lib.rs","byte_start":212,"byte_end":229,"line_start":8,"line_end":8,"column_start":1,"column_end":18}},{"value":"/","span":{"file_name":"/home/nick12345/.cargo/registry/src/github.com-1ecc6299db9ec823/gql_client-1.0.7/src/lib.rs","byte_start":230,"byte_end":233,"line_start":9,"line_end":9,"column_start":1,"column_end":4}},{"value":"/ * Use client.query_with_vars for queries with variables","span":{"file_name":"/home/nick12345/.cargo/registry/src/github.com-1ecc6299db9ec823/gql_client-1.0.7/src/lib.rs","byte_start":234,"byte_end":293,"line_start":10,"line_end":10,"column_start":1,"column_end":60}},{"value":"/ * There's also a wrapper client.query if there is no need to pass variables","span":{"file_name":"/home/nick12345/.cargo/registry/src/github.com-1ecc6299db9ec823/gql_client-1.0.7/src/lib.rs","byte_start":294,"byte_end":373,"line_start":11,"line_end":11,"column_start":1,"column_end":80}},{"value":"/","span":{"file_name":"/home/nick12345/.cargo/registry/src/github.com-1ecc6299db9ec823/gql_client-1.0.7/src/lib.rs","byte_start":374,"byte_end":377,"line_start":12,"line_end":12,"column_start":1,"column_end":4}},{"value":"/ ```rust","span":{"file_name":"/home/nick12345/.cargo/registry/src/github.com-1ecc6299db9ec823/gql_client-1.0.7/src/lib.rs","byte_start":378,"byte_end":389,"line_start":13,"line_end":13,"column_start":1,"column_end":12}},{"value":"/use gql_client::Client;","span":{"file_name":"/home/nick12345/.cargo/registry/src/github.com-1ecc6299db9ec823/gql_client-1.0.7/src/lib.rs","byte_start":390,"byte_end":416,"line_start":14,"line_end":14,"column_start":1,"column_end":27}},{"value":"/use serde::{Deserialize, Serialize};","span":{"file_name":"/home/nick12345/.cargo/registry/src/github.com-1ecc6299db9ec823/gql_client-1.0.7/src/lib.rs","byte_start":417,"byte_end":456,"line_start":15,"line_end":15,"column_start":1,"column_end":40}},{"value":"/","span":{"file_name":"/home/nick12345/.cargo/registry/src/github.com-1ecc6299db9ec823/gql_client-1.0.7/src/lib.rs","byte_start":457,"byte_end":460,"line_start":16,"line_end":16,"column_start":1,"column_end":4}},{"value":"/#[derive(Deserialize)]","span":{"file_name":"/home/nick12345/.cargo/registry/src/github.com-1ecc6299db9ec823/gql_client-1.0.7/src/lib.rs","byte_start":461,"byte_end":486,"line_start":17,"line_end":17,"column_start":1,"column_end":26}},{"value":"/pub struct Data {","span":{"file_name":"/home/nick12345/.cargo/registry/src/github.com-1ecc6299db9ec823/gql_client-1.0.7/src/lib.rs","byte_start":487,"byte_end":507,"line_start":18,"line_end":18,"column_start":1,"column_end":21}},{"value":"/    user: User","span":{"file_name":"/home/nick12345/.cargo/registry/src/github.com-1ecc6299db9ec823/gql_client-1.0.7/src/lib.rs","byte_start":508,"byte_end":525,"line_start":19,"line_end":19,"column_start":1,"column_end":18}},{"value":"/}","span":{"file_name":"/home/nick12345/.cargo/registry/src/github.com-1ecc6299db9ec823/gql_client-1.0.7/src/lib.rs","byte_start":526,"byte_end":530,"line_start":20,"line_end":20,"column_start":1,"column_end":5}},{"value":"/","span":{"file_name":"/home/nick12345/.cargo/registry/src/github.com-1ecc6299db9ec823/gql_client-1.0.7/src/lib.rs","byte_start":531,"byte_end":534,"line_start":21,"line_end":21,"column_start":1,"column_end":4}},{"value":"/#[derive(Deserialize)]","span":{"file_name":"/home/nick12345/.cargo/registry/src/github.com-1ecc6299db9ec823/gql_client-1.0.7/src/lib.rs","byte_start":535,"byte_end":560,"line_start":22,"line_end":22,"column_start":1,"column_end":26}},{"value":"/pub struct User {","span":{"file_name":"/home/nick12345/.cargo/registry/src/github.com-1ecc6299db9ec823/gql_client-1.0.7/src/lib.rs","byte_start":561,"byte_end":581,"line_start":23,"line_end":23,"column_start":1,"column_end":21}},{"value":"/    id: String,","span":{"file_name":"/home/nick12345/.cargo/registry/src/github.com-1ecc6299db9ec823/gql_client-1.0.7/src/lib.rs","byte_start":582,"byte_end":600,"line_start":24,"line_end":24,"column_start":1,"column_end":19}},{"value":"/    name: String","span":{"file_name":"/home/nick12345/.cargo/registry/src/github.com-1ecc6299db9ec823/gql_client-1.0.7/src/lib.rs","byte_start":601,"byte_end":620,"line_start":25,"line_end":25,"column_start":1,"column_end":20}},{"value":"/}","span":{"file_name":"/home/nick12345/.cargo/registry/src/github.com-1ecc6299db9ec823/gql_client-1.0.7/src/lib.rs","byte_start":621,"byte_end":625,"line_start":26,"line_end":26,"column_start":1,"column_end":5}},{"value":"/","span":{"file_name":"/home/nick12345/.cargo/registry/src/github.com-1ecc6299db9ec823/gql_client-1.0.7/src/lib.rs","byte_start":626,"byte_end":629,"line_start":27,"line_end":27,"column_start":1,"column_end":4}},{"value":"/#[derive(Serialize)]","span":{"file_name":"/home/nick12345/.cargo/registry/src/github.com-1ecc6299db9ec823/gql_client-1.0.7/src/lib.rs","byte_start":630,"byte_end":653,"line_start":28,"line_end":28,"column_start":1,"column_end":24}},{"value":"/pub struct Vars {","span":{"file_name":"/home/nick12345/.cargo/registry/src/github.com-1ecc6299db9ec823/gql_client-1.0.7/src/lib.rs","byte_start":654,"byte_end":674,"line_start":29,"line_end":29,"column_start":1,"column_end":21}},{"value":"/    id: u32","span":{"file_name":"/home/nick12345/.cargo/registry/src/github.com-1ecc6299db9ec823/gql_client-1.0.7/src/lib.rs","byte_start":675,"byte_end":689,"line_start":30,"line_end":30,"column_start":1,"column_end":15}},{"value":"/}","span":{"file_name":"/home/nick12345/.cargo/registry/src/github.com-1ecc6299db9ec823/gql_client-1.0.7/src/lib.rs","byte_start":690,"byte_end":694,"line_start":31,"line_end":31,"column_start":1,"column_end":5}},{"value":"/","span":{"file_name":"/home/nick12345/.cargo/registry/src/github.com-1ecc6299db9ec823/gql_client-1.0.7/src/lib.rs","byte_start":695,"byte_end":698,"line_start":32,"line_end":32,"column_start":1,"column_end":4}},{"value":"/#[tokio::main]","span":{"file_name":"/home/nick12345/.cargo/registry/src/github.com-1ecc6299db9ec823/gql_client-1.0.7/src/lib.rs","byte_start":699,"byte_end":716,"line_start":33,"line_end":33,"column_start":1,"column_end":18}},{"value":"/async fn main() -> Result<(), Box<dyn std::error::Error>> {","span":{"file_name":"/home/nick12345/.cargo/registry/src/github.com-1ecc6299db9ec823/gql_client-1.0.7/src/lib.rs","byte_start":717,"byte_end":779,"line_start":34,"line_end":34,"column_start":1,"column_end":63}},{"value":"/    let endpoint = \"https://graphqlzero.almansi.me/api\";","span":{"file_name":"/home/nick12345/.cargo/registry/src/github.com-1ecc6299db9ec823/gql_client-1.0.7/src/lib.rs","byte_start":780,"byte_end":839,"line_start":35,"line_end":35,"column_start":1,"column_end":60}},{"value":"/    let query = r#\"","span":{"file_name":"/home/nick12345/.cargo/registry/src/github.com-1ecc6299db9ec823/gql_client-1.0.7/src/lib.rs","byte_start":840,"byte_end":862,"line_start":36,"line_end":36,"column_start":1,"column_end":23}},{"value":"/        query UserByIdQuery($id: ID!) {","span":{"file_name":"/home/nick12345/.cargo/registry/src/github.com-1ecc6299db9ec823/gql_client-1.0.7/src/lib.rs","byte_start":863,"byte_end":905,"line_start":37,"line_end":37,"column_start":1,"column_end":43}},{"value":"/            user(id: $id) {","span":{"file_name":"/home/nick12345/.cargo/registry/src/github.com-1ecc6299db9ec823/gql_client-1.0.7/src/lib.rs","byte_start":906,"byte_end":936,"line_start":38,"line_end":38,"column_start":1,"column_end":31}},{"value":"/                id","span":{"file_name":"/home/nick12345/.cargo/registry/src/github.com-1ecc6299db9ec823/gql_client-1.0.7/src/lib.rs","byte_start":937,"byte_end":958,"line_start":39,"line_end":39,"column_start":1,"column_end":22}},{"value":"/                name","span":{"file_name":"/home/nick12345/.cargo/registry/src/github.com-1ecc6299db9ec823/gql_client-1.0.7/src/lib.rs","byte_start":959,"byte_end":982,"line_start":40,"line_end":40,"column_start":1,"column_end":24}},{"value":"/            }","span":{"file_name":"/home/nick12345/.cargo/registry/src/github.com-1ecc6299db9ec823/gql_client-1.0.7/src/lib.rs","byte_start":983,"byte_end":999,"line_start":41,"line_end":41,"column_start":1,"column_end":17}},{"value":"/        }","span":{"file_name":"/home/nick12345/.cargo/registry/src/github.com-1ecc6299db9ec823/gql_client-1.0.7/src/lib.rs","byte_start":1000,"byte_end":1012,"line_start":42,"line_end":42,"column_start":1,"column_end":13}},{"value":"/    \"#;","span":{"file_name":"/home/nick12345/.cargo/registry/src/github.com-1ecc6299db9ec823/gql_client-1.0.7/src/lib.rs","byte_start":1013,"byte_end":1023,"line_start":43,"line_end":43,"column_start":1,"column_end":11}},{"value":"/","span":{"file_name":"/home/nick12345/.cargo/registry/src/github.com-1ecc6299db9ec823/gql_client-1.0.7/src/lib.rs","byte_start":1024,"byte_end":1027,"line_start":44,"line_end":44,"column_start":1,"column_end":4}},{"value":"/    let client = Client::new(endpoint);","span":{"file_name":"/home/nick12345/.cargo/registry/src/github.com-1ecc6299db9ec823/gql_client-1.0.7/src/lib.rs","byte_start":1028,"byte_end":1070,"line_start":45,"line_end":45,"column_start":1,"column_end":43}},{"value":"/    let vars = Vars { id: 1 };","span":{"file_name":"/home/nick12345/.cargo/registry/src/github.com-1ecc6299db9ec823/gql_client-1.0.7/src/lib.rs","byte_start":1071,"byte_end":1104,"line_start":46,"line_end":46,"column_start":1,"column_end":34}},{"value":"/    let data = client.query_with_vars_unwrap::<Data, Vars>(query, vars).await.unwrap();","span":{"file_name":"/home/nick12345/.cargo/registry/src/github.com-1ecc6299db9ec823/gql_client-1.0.7/src/lib.rs","byte_start":1105,"byte_end":1195,"line_start":47,"line_end":47,"column_start":1,"column_end":91}},{"value":"/","span":{"file_name":"/home/nick12345/.cargo/registry/src/github.com-1ecc6299db9ec823/gql_client-1.0.7/src/lib.rs","byte_start":1196,"byte_end":1199,"line_start":48,"line_end":48,"column_start":1,"column_end":4}},{"value":"/    println!(\"Id: {}, Name: {}\", data.user.id, data.user.name);","span":{"file_name":"/home/nick12345/.cargo/registry/src/github.com-1ecc6299db9ec823/gql_client-1.0.7/src/lib.rs","byte_start":1200,"byte_end":1266,"line_start":49,"line_end":49,"column_start":1,"column_end":67}},{"value":"/","span":{"file_name":"/home/nick12345/.cargo/registry/src/github.com-1ecc6299db9ec823/gql_client-1.0.7/src/lib.rs","byte_start":1267,"byte_end":1270,"line_start":50,"line_end":50,"column_start":1,"column_end":4}},{"value":"/    Ok(())","span":{"file_name":"/home/nick12345/.cargo/registry/src/github.com-1ecc6299db9ec823/gql_client-1.0.7/src/lib.rs","byte_start":1271,"byte_end":1284,"line_start":51,"line_end":51,"column_start":1,"column_end":14}},{"value":"/}","span":{"file_name":"/home/nick12345/.cargo/registry/src/github.com-1ecc6299db9ec823/gql_client-1.0.7/src/lib.rs","byte_start":1285,"byte_end":1289,"line_start":52,"line_end":52,"column_start":1,"column_end":5}},{"value":"/ ```","span":{"file_name":"/home/nick12345/.cargo/registry/src/github.com-1ecc6299db9ec823/gql_client-1.0.7/src/lib.rs","byte_start":1290,"byte_end":1297,"line_start":53,"line_end":53,"column_start":1,"column_end":8}},{"value":"/","span":{"file_name":"/home/nick12345/.cargo/registry/src/github.com-1ecc6299db9ec823/gql_client-1.0.7/src/lib.rs","byte_start":1298,"byte_end":1301,"line_start":54,"line_end":54,"column_start":1,"column_end":4}},{"value":"/","span":{"file_name":"/home/nick12345/.cargo/registry/src/github.com-1ecc6299db9ec823/gql_client-1.0.7/src/lib.rs","byte_start":1302,"byte_end":1305,"line_start":55,"line_end":55,"column_start":1,"column_end":4}},{"value":"/ # Passing HTTP headers","span":{"file_name":"/home/nick12345/.cargo/registry/src/github.com-1ecc6299db9ec823/gql_client-1.0.7/src/lib.rs","byte_start":1306,"byte_end":1332,"line_start":56,"line_end":56,"column_start":1,"column_end":27}},{"value":"/","span":{"file_name":"/home/nick12345/.cargo/registry/src/github.com-1ecc6299db9ec823/gql_client-1.0.7/src/lib.rs","byte_start":1333,"byte_end":1336,"line_start":57,"line_end":57,"column_start":1,"column_end":4}},{"value":"/ Client exposes new_with_headers function to pass headers","span":{"file_name":"/home/nick12345/.cargo/registry/src/github.com-1ecc6299db9ec823/gql_client-1.0.7/src/lib.rs","byte_start":1337,"byte_end":1397,"line_start":58,"line_end":58,"column_start":1,"column_end":61}},{"value":"/ using simple HashMap<&str, &str>","span":{"file_name":"/home/nick12345/.cargo/registry/src/github.com-1ecc6299db9ec823/gql_client-1.0.7/src/lib.rs","byte_start":1398,"byte_end":1434,"line_start":59,"line_end":59,"column_start":1,"column_end":37}},{"value":"/","span":{"file_name":"/home/nick12345/.cargo/registry/src/github.com-1ecc6299db9ec823/gql_client-1.0.7/src/lib.rs","byte_start":1435,"byte_end":1438,"line_start":60,"line_end":60,"column_start":1,"column_end":4}},{"value":"/ ```rust","span":{"file_name":"/home/nick12345/.cargo/registry/src/github.com-1ecc6299db9ec823/gql_client-1.0.7/src/lib.rs","byte_start":1439,"byte_end":1450,"line_start":61,"line_end":61,"column_start":1,"column_end":12}},{"value":"/use gql_client::Client;","span":{"file_name":"/home/nick12345/.cargo/registry/src/github.com-1ecc6299db9ec823/gql_client-1.0.7/src/lib.rs","byte_start":1451,"byte_end":1477,"line_start":62,"line_end":62,"column_start":1,"column_end":27}},{"value":"/use std::collections::HashMap;","span":{"file_name":"/home/nick12345/.cargo/registry/src/github.com-1ecc6299db9ec823/gql_client-1.0.7/src/lib.rs","byte_start":1478,"byte_end":1511,"line_start":63,"line_end":63,"column_start":1,"column_end":34}},{"value":"/","span":{"file_name":"/home/nick12345/.cargo/registry/src/github.com-1ecc6299db9ec823/gql_client-1.0.7/src/lib.rs","byte_start":1512,"byte_end":1515,"line_start":64,"line_end":64,"column_start":1,"column_end":4}},{"value":"/#[tokio::main]","span":{"file_name":"/home/nick12345/.cargo/registry/src/github.com-1ecc6299db9ec823/gql_client-1.0.7/src/lib.rs","byte_start":1516,"byte_end":1533,"line_start":65,"line_end":65,"column_start":1,"column_end":18}},{"value":"/async fn main() -> Result<(), Box<dyn std::error::Error>> {","span":{"file_name":"/home/nick12345/.cargo/registry/src/github.com-1ecc6299db9ec823/gql_client-1.0.7/src/lib.rs","byte_start":1534,"byte_end":1596,"line_start":66,"line_end":66,"column_start":1,"column_end":63}},{"value":"/    let endpoint = \"https://graphqlzero.almansi.me/api\";","span":{"file_name":"/home/nick12345/.cargo/registry/src/github.com-1ecc6299db9ec823/gql_client-1.0.7/src/lib.rs","byte_start":1597,"byte_end":1656,"line_start":67,"line_end":67,"column_start":1,"column_end":60}},{"value":"/    let mut headers = HashMap::new();","span":{"file_name":"/home/nick12345/.cargo/registry/src/github.com-1ecc6299db9ec823/gql_client-1.0.7/src/lib.rs","byte_start":1657,"byte_end":1697,"line_start":68,"line_end":68,"column_start":1,"column_end":41}},{"value":"/    headers.insert(\"authorization\", \"Bearer <some_token>\");","span":{"file_name":"/home/nick12345/.cargo/registry/src/github.com-1ecc6299db9ec823/gql_client-1.0.7/src/lib.rs","byte_start":1698,"byte_end":1760,"line_start":69,"line_end":69,"column_start":1,"column_end":63}},{"value":"/","span":{"file_name":"/home/nick12345/.cargo/registry/src/github.com-1ecc6299db9ec823/gql_client-1.0.7/src/lib.rs","byte_start":1761,"byte_end":1764,"line_start":70,"line_end":70,"column_start":1,"column_end":4}},{"value":"/    let client = Client::new_with_headers(endpoint, headers);","span":{"file_name":"/home/nick12345/.cargo/registry/src/github.com-1ecc6299db9ec823/gql_client-1.0.7/src/lib.rs","byte_start":1765,"byte_end":1829,"line_start":71,"line_end":71,"column_start":1,"column_end":65}},{"value":"/","span":{"file_name":"/home/nick12345/.cargo/registry/src/github.com-1ecc6299db9ec823/gql_client-1.0.7/src/lib.rs","byte_start":1830,"byte_end":1833,"line_start":72,"line_end":72,"column_start":1,"column_end":4}},{"value":"/    Ok(())","span":{"file_name":"/home/nick12345/.cargo/registry/src/github.com-1ecc6299db9ec823/gql_client-1.0.7/src/lib.rs","byte_start":1834,"byte_end":1847,"line_start":73,"line_end":73,"column_start":1,"column_end":14}},{"value":"/}","span":{"file_name":"/home/nick12345/.cargo/registry/src/github.com-1ecc6299db9ec823/gql_client-1.0.7/src/lib.rs","byte_start":1848,"byte_end":1852,"line_start":74,"line_end":74,"column_start":1,"column_end":5}},{"value":"/ ```","span":{"file_name":"/home/nick12345/.cargo/registry/src/github.com-1ecc6299db9ec823/gql_client-1.0.7/src/lib.rs","byte_start":1853,"byte_end":1860,"line_start":75,"line_end":75,"column_start":1,"column_end":8}},{"value":"/","span":{"file_name":"/home/nick12345/.cargo/registry/src/github.com-1ecc6299db9ec823/gql_client-1.0.7/src/lib.rs","byte_start":1861,"byte_end":1864,"line_start":76,"line_end":76,"column_start":1,"column_end":4}},{"value":"/ # Error handling","span":{"file_name":"/home/nick12345/.cargo/registry/src/github.com-1ecc6299db9ec823/gql_client-1.0.7/src/lib.rs","byte_start":1865,"byte_end":1885,"line_start":77,"line_end":77,"column_start":1,"column_end":21}},{"value":"/ There are two types of errors that can possibly occur. HTTP related errors (for example, authentication problem)","span":{"file_name":"/home/nick12345/.cargo/registry/src/github.com-1ecc6299db9ec823/gql_client-1.0.7/src/lib.rs","byte_start":1886,"byte_end":2002,"line_start":78,"line_end":78,"column_start":1,"column_end":117}},{"value":"/ or GraphQL query errors in JSON response.","span":{"file_name":"/home/nick12345/.cargo/registry/src/github.com-1ecc6299db9ec823/gql_client-1.0.7/src/lib.rs","byte_start":2003,"byte_end":2048,"line_start":79,"line_end":79,"column_start":1,"column_end":46}},{"value":"/ Debug, Display implementation of GraphQLError struct properly displays those error messages.","span":{"file_name":"/home/nick12345/.cargo/registry/src/github.com-1ecc6299db9ec823/gql_client-1.0.7/src/lib.rs","byte_start":2049,"byte_end":2145,"line_start":80,"line_end":80,"column_start":1,"column_end":97}},{"value":"/ Additionally, you can also look at JSON content for more detailed output by calling err.json()","span":{"file_name":"/home/nick12345/.cargo/registry/src/github.com-1ecc6299db9ec823/gql_client-1.0.7/src/lib.rs","byte_start":2146,"byte_end":2244,"line_start":81,"line_end":81,"column_start":1,"column_end":99}},{"value":"/","span":{"file_name":"/home/nick12345/.cargo/registry/src/github.com-1ecc6299db9ec823/gql_client-1.0.7/src/lib.rs","byte_start":2245,"byte_end":2248,"line_start":82,"line_end":82,"column_start":1,"column_end":4}},{"value":"/ ```rust","span":{"file_name":"/home/nick12345/.cargo/registry/src/github.com-1ecc6299db9ec823/gql_client-1.0.7/src/lib.rs","byte_start":2249,"byte_end":2260,"line_start":83,"line_end":83,"column_start":1,"column_end":12}},{"value":"/use gql_client::Client;","span":{"file_name":"/home/nick12345/.cargo/registry/src/github.com-1ecc6299db9ec823/gql_client-1.0.7/src/lib.rs","byte_start":2261,"byte_end":2287,"line_start":84,"line_end":84,"column_start":1,"column_end":27}},{"value":"/use serde::{Deserialize, Serialize};","span":{"file_name":"/home/nick12345/.cargo/registry/src/github.com-1ecc6299db9ec823/gql_client-1.0.7/src/lib.rs","byte_start":2288,"byte_end":2327,"line_start":85,"line_end":85,"column_start":1,"column_end":40}},{"value":"/","span":{"file_name":"/home/nick12345/.cargo/registry/src/github.com-1ecc6299db9ec823/gql_client-1.0.7/src/lib.rs","byte_start":2328,"byte_end":2331,"line_start":86,"line_end":86,"column_start":1,"column_end":4}},{"value":"/#[derive(Deserialize)]","span":{"file_name":"/home/nick12345/.cargo/registry/src/github.com-1ecc6299db9ec823/gql_client-1.0.7/src/lib.rs","byte_start":2332,"byte_end":2357,"line_start":87,"line_end":87,"column_start":1,"column_end":26}},{"value":"/pub struct Data {","span":{"file_name":"/home/nick12345/.cargo/registry/src/github.com-1ecc6299db9ec823/gql_client-1.0.7/src/lib.rs","byte_start":2358,"byte_end":2378,"line_start":88,"line_end":88,"column_start":1,"column_end":21}},{"value":"/    user: User","span":{"file_name":"/home/nick12345/.cargo/registry/src/github.com-1ecc6299db9ec823/gql_client-1.0.7/src/lib.rs","byte_start":2379,"byte_end":2396,"line_start":89,"line_end":89,"column_start":1,"column_end":18}},{"value":"/}","span":{"file_name":"/home/nick12345/.cargo/registry/src/github.com-1ecc6299db9ec823/gql_client-1.0.7/src/lib.rs","byte_start":2397,"byte_end":2401,"line_start":90,"line_end":90,"column_start":1,"column_end":5}},{"value":"/","span":{"file_name":"/home/nick12345/.cargo/registry/src/github.com-1ecc6299db9ec823/gql_client-1.0.7/src/lib.rs","byte_start":2402,"byte_end":2405,"line_start":91,"line_end":91,"column_start":1,"column_end":4}},{"value":"/#[derive(Deserialize)]","span":{"file_name":"/home/nick12345/.cargo/registry/src/github.com-1ecc6299db9ec823/gql_client-1.0.7/src/lib.rs","byte_start":2406,"byte_end":2431,"line_start":92,"line_end":92,"column_start":1,"column_end":26}},{"value":"/pub struct User {","span":{"file_name":"/home/nick12345/.cargo/registry/src/github.com-1ecc6299db9ec823/gql_client-1.0.7/src/lib.rs","byte_start":2432,"byte_end":2452,"line_start":93,"line_end":93,"column_start":1,"column_end":21}},{"value":"/    id: String,","span":{"file_name":"/home/nick12345/.cargo/registry/src/github.com-1ecc6299db9ec823/gql_client-1.0.7/src/lib.rs","byte_start":2453,"byte_end":2471,"line_start":94,"line_end":94,"column_start":1,"column_end":19}},{"value":"/    name: String","span":{"file_name":"/home/nick12345/.cargo/registry/src/github.com-1ecc6299db9ec823/gql_client-1.0.7/src/lib.rs","byte_start":2472,"byte_end":2491,"line_start":95,"line_end":95,"column_start":1,"column_end":20}},{"value":"/}","span":{"file_name":"/home/nick12345/.cargo/registry/src/github.com-1ecc6299db9ec823/gql_client-1.0.7/src/lib.rs","byte_start":2492,"byte_end":2496,"line_start":96,"line_end":96,"column_start":1,"column_end":5}},{"value":"/","span":{"file_name":"/home/nick12345/.cargo/registry/src/github.com-1ecc6299db9ec823/gql_client-1.0.7/src/lib.rs","byte_start":2497,"byte_end":2500,"line_start":97,"line_end":97,"column_start":1,"column_end":4}},{"value":"/#[derive(Serialize)]","span":{"file_name":"/home/nick12345/.cargo/registry/src/github.com-1ecc6299db9ec823/gql_client-1.0.7/src/lib.rs","byte_start":2501,"byte_end":2524,"line_start":98,"line_end":98,"column_start":1,"column_end":24}},{"value":"/pub struct Vars {","span":{"file_name":"/home/nick12345/.cargo/registry/src/github.com-1ecc6299db9ec823/gql_client-1.0.7/src/lib.rs","byte_start":2525,"byte_end":2545,"line_start":99,"line_end":99,"column_start":1,"column_end":21}},{"value":"/    id: u32","span":{"file_name":"/home/nick12345/.cargo/registry/src/github.com-1ecc6299db9ec823/gql_client-1.0.7/src/lib.rs","byte_start":2546,"byte_end":2560,"line_start":100,"line_end":100,"column_start":1,"column_end":15}},{"value":"/}","span":{"file_name":"/home/nick12345/.cargo/registry/src/github.com-1ecc6299db9ec823/gql_client-1.0.7/src/lib.rs","byte_start":2561,"byte_end":2565,"line_start":101,"line_end":101,"column_start":1,"column_end":5}},{"value":"/","span":{"file_name":"/home/nick12345/.cargo/registry/src/github.com-1ecc6299db9ec823/gql_client-1.0.7/src/lib.rs","byte_start":2566,"byte_end":2569,"line_start":102,"line_end":102,"column_start":1,"column_end":4}},{"value":"/#[tokio::main]","span":{"file_name":"/home/nick12345/.cargo/registry/src/github.com-1ecc6299db9ec823/gql_client-1.0.7/src/lib.rs","byte_start":2570,"byte_end":2587,"line_start":103,"line_end":103,"column_start":1,"column_end":18}},{"value":"/async fn main() -> Result<(), Box<dyn std::error::Error>> {","span":{"file_name":"/home/nick12345/.cargo/registry/src/github.com-1ecc6299db9ec823/gql_client-1.0.7/src/lib.rs","byte_start":2588,"byte_end":2650,"line_start":104,"line_end":104,"column_start":1,"column_end":63}},{"value":"/    let endpoint = \"https://graphqlzero.almansi.me/api\";","span":{"file_name":"/home/nick12345/.cargo/registry/src/github.com-1ecc6299db9ec823/gql_client-1.0.7/src/lib.rs","byte_start":2651,"byte_end":2710,"line_start":105,"line_end":105,"column_start":1,"column_end":60}},{"value":"/","span":{"file_name":"/home/nick12345/.cargo/registry/src/github.com-1ecc6299db9ec823/gql_client-1.0.7/src/lib.rs","byte_start":2711,"byte_end":2714,"line_start":106,"line_end":106,"column_start":1,"column_end":4}},{"value":"/    // Send incorrect request","span":{"file_name":"/home/nick12345/.cargo/registry/src/github.com-1ecc6299db9ec823/gql_client-1.0.7/src/lib.rs","byte_start":2715,"byte_end":2747,"line_start":107,"line_end":107,"column_start":1,"column_end":33}},{"value":"/    let query = r#\"","span":{"file_name":"/home/nick12345/.cargo/registry/src/github.com-1ecc6299db9ec823/gql_client-1.0.7/src/lib.rs","byte_start":2748,"byte_end":2770,"line_start":108,"line_end":108,"column_start":1,"column_end":23}},{"value":"/        query UserByIdQuery($id: ID!) {","span":{"file_name":"/home/nick12345/.cargo/registry/src/github.com-1ecc6299db9ec823/gql_client-1.0.7/src/lib.rs","byte_start":2771,"byte_end":2813,"line_start":109,"line_end":109,"column_start":1,"column_end":43}},{"value":"/            user(id: $id) {","span":{"file_name":"/home/nick12345/.cargo/registry/src/github.com-1ecc6299db9ec823/gql_client-1.0.7/src/lib.rs","byte_start":2814,"byte_end":2844,"line_start":110,"line_end":110,"column_start":1,"column_end":31}},{"value":"/                id1","span":{"file_name":"/home/nick12345/.cargo/registry/src/github.com-1ecc6299db9ec823/gql_client-1.0.7/src/lib.rs","byte_start":2845,"byte_end":2867,"line_start":111,"line_end":111,"column_start":1,"column_end":23}},{"value":"/                name","span":{"file_name":"/home/nick12345/.cargo/registry/src/github.com-1ecc6299db9ec823/gql_client-1.0.7/src/lib.rs","byte_start":2868,"byte_end":2891,"line_start":112,"line_end":112,"column_start":1,"column_end":24}},{"value":"/            }","span":{"file_name":"/home/nick12345/.cargo/registry/src/github.com-1ecc6299db9ec823/gql_client-1.0.7/src/lib.rs","byte_start":2892,"byte_end":2908,"line_start":113,"line_end":113,"column_start":1,"column_end":17}},{"value":"/        }","span":{"file_name":"/home/nick12345/.cargo/registry/src/github.com-1ecc6299db9ec823/gql_client-1.0.7/src/lib.rs","byte_start":2909,"byte_end":2921,"line_start":114,"line_end":114,"column_start":1,"column_end":13}},{"value":"/    \"#;","span":{"file_name":"/home/nick12345/.cargo/registry/src/github.com-1ecc6299db9ec823/gql_client-1.0.7/src/lib.rs","byte_start":2922,"byte_end":2932,"line_start":115,"line_end":115,"column_start":1,"column_end":11}},{"value":"/","span":{"file_name":"/home/nick12345/.cargo/registry/src/github.com-1ecc6299db9ec823/gql_client-1.0.7/src/lib.rs","byte_start":2933,"byte_end":2936,"line_start":116,"line_end":116,"column_start":1,"column_end":4}},{"value":"/    let client = Client::new(endpoint);","span":{"file_name":"/home/nick12345/.cargo/registry/src/github.com-1ecc6299db9ec823/gql_client-1.0.7/src/lib.rs","byte_start":2937,"byte_end":2979,"line_start":117,"line_end":117,"column_start":1,"column_end":43}},{"value":"/    let vars = Vars { id: 1 };","span":{"file_name":"/home/nick12345/.cargo/registry/src/github.com-1ecc6299db9ec823/gql_client-1.0.7/src/lib.rs","byte_start":2980,"byte_end":3013,"line_start":118,"line_end":118,"column_start":1,"column_end":34}},{"value":"/    let error = client.query_with_vars::<Data, Vars>(query, vars).await.err();","span":{"file_name":"/home/nick12345/.cargo/registry/src/github.com-1ecc6299db9ec823/gql_client-1.0.7/src/lib.rs","byte_start":3014,"byte_end":3095,"line_start":119,"line_end":119,"column_start":1,"column_end":82}},{"value":"/","span":{"file_name":"/home/nick12345/.cargo/registry/src/github.com-1ecc6299db9ec823/gql_client-1.0.7/src/lib.rs","byte_start":3096,"byte_end":3099,"line_start":120,"line_end":120,"column_start":1,"column_end":4}},{"value":"/    println!(\"{:?}\", error);","span":{"file_name":"/home/nick12345/.cargo/registry/src/github.com-1ecc6299db9ec823/gql_client-1.0.7/src/lib.rs","byte_start":3100,"byte_end":3131,"line_start":121,"line_end":121,"column_start":1,"column_end":32}},{"value":"/","span":{"file_name":"/home/nick12345/.cargo/registry/src/github.com-1ecc6299db9ec823/gql_client-1.0.7/src/lib.rs","byte_start":3132,"byte_end":3135,"line_start":122,"line_end":122,"column_start":1,"column_end":4}},{"value":"/    Ok(())","span":{"file_name":"/home/nick12345/.cargo/registry/src/github.com-1ecc6299db9ec823/gql_client-1.0.7/src/lib.rs","byte_start":3136,"byte_end":3149,"line_start":123,"line_end":123,"column_start":1,"column_end":14}},{"value":"/}","span":{"file_name":"/home/nick12345/.cargo/registry/src/github.com-1ecc6299db9ec823/gql_client-1.0.7/src/lib.rs","byte_start":3150,"byte_end":3154,"line_start":124,"line_end":124,"column_start":1,"column_end":5}},{"value":"/ ```","span":{"file_name":"/home/nick12345/.cargo/registry/src/github.com-1ecc6299db9ec823/gql_client-1.0.7/src/lib.rs","byte_start":3155,"byte_end":3162,"line_start":125,"line_end":125,"column_start":1,"column_end":8}}]},{"kind":"Struct","id":{"krate":0,"index":147},"span":{"file_name":"/home/nick12345/.cargo/registry/src/github.com-1ecc6299db9ec823/gql_client-1.0.7/src/client.rs","byte_start":3620,"byte_end":3629,"line_start":13,"line_end":13,"column_start":12,"column_end":21},"name":"GQLClient","qualname":"::client::GQLClient","value":"GQLClient {  }","parent":null,"children":[{"krate":0,"index":148}],"decl_id":null,"docs":"","sig":null,"attributes":[]},{"kind":"Method","id":{"krate":0,"index":41},"span":{"file_name":"/home/nick12345/.cargo/registry/src/github.com-1ecc6299db9ec823/gql_client-1.0.7/src/client.rs","byte_start":4481,"byte_end":4484,"line_start":50,"line_end":50,"column_start":10,"column_end":13},"name":"new","qualname":"<GQLClient>::new","value":"fn new<impl AsRef<str>>(impl AsRef<str>) -> Self where\nimpl AsRef<str>: AsRef<str>","parent":null,"children":[],"decl_id":null,"docs":"","sig":null,"attributes":[]},{"kind":"Method","id":{"krate":0,"index":43},"span":{"file_name":"/home/nick12345/.cargo/registry/src/github.com-1ecc6299db9ec823/gql_client-1.0.7/src/client.rs","byte_start":4721,"byte_end":4737,"line_start":61,"line_end":61,"column_start":10,"column_end":26},"name":"new_with_headers","qualname":"<GQLClient>::new_with_headers","value":"fn new_with_headers<impl AsRef<str>, impl ToString,\nimpl ToString>(impl AsRef<str>, HashMap<impl ToString, impl ToString>) -> Self\nwhere impl AsRef<str>: AsRef<str>, impl ToString: ToString,\nimpl ToString: ToString","parent":null,"children":[],"decl_id":null,"docs":"","sig":null,"attributes":[]},{"kind":"Method","id":{"krate":0,"index":48},"span":{"file_name":"/home/nick12345/.cargo/registry/src/github.com-1ecc6299db9ec823/gql_client-1.0.7/src/client.rs","byte_start":5200,"byte_end":5215,"line_start":80,"line_end":80,"column_start":10,"column_end":25},"name":"new_with_config","qualname":"<GQLClient>::new_with_config","value":"fn new_with_config(ClientConfig) -> Self","parent":null,"children":[],"decl_id":null,"docs":"","sig":null,"attributes":[]},{"kind":"Method","id":{"krate":0,"index":50},"span":{"file_name":"/home/nick12345/.cargo/registry/src/github.com-1ecc6299db9ec823/gql_client-1.0.7/src/client.rs","byte_start":5307,"byte_end":5312,"line_start":86,"line_end":86,"column_start":16,"column_end":21},"name":"query","qualname":"<GQLClient>::query","value":"async fn query<K, '_, '_>(&'_ Self, &'_ str) -> /*impl Trait*/ where\nK: for<'de> Deserialize","parent":null,"children":[],"decl_id":null,"docs":"","sig":null,"attributes":[]},{"kind":"Method","id":{"krate":0,"index":55},"span":{"file_name":"/home/nick12345/.cargo/registry/src/github.com-1ecc6299db9ec823/gql_client-1.0.7/src/client.rs","byte_start":5488,"byte_end":5500,"line_start":93,"line_end":93,"column_start":16,"column_end":28},"name":"query_unwrap","qualname":"<GQLClient>::query_unwrap","value":"async fn query_unwrap<K, '_, '_>(&'_ Self, &'_ str) -> /*impl Trait*/ where\nK: for<'de> Deserialize","parent":null,"children":[],"decl_id":null,"docs":"","sig":null,"attributes":[]},{"kind":"Method","id":{"krate":0,"index":60},"span":{"file_name":"/home/nick12345/.cargo/registry/src/github.com-1ecc6299db9ec823/gql_client-1.0.7/src/client.rs","byte_start":5675,"byte_end":5697,"line_start":100,"line_end":100,"column_start":16,"column_end":38},"name":"query_with_vars_unwrap","qualname":"<GQLClient>::query_with_vars_unwrap","value":"async fn query_with_vars_unwrap<K, T, '_, '_>(&'_ Self, &'_ str, T)\n-> /*impl Trait*/ where T: Serialize, K: for<'de> Deserialize","parent":null,"children":[],"decl_id":null,"docs":"","sig":null,"attributes":[]},{"kind":"Method","id":{"krate":0,"index":66},"span":{"file_name":"/home/nick12345/.cargo/registry/src/github.com-1ecc6299db9ec823/gql_client-1.0.7/src/client.rs","byte_start":6096,"byte_end":6111,"line_start":117,"line_end":117,"column_start":16,"column_end":31},"name":"query_with_vars","qualname":"<GQLClient>::query_with_vars","value":"async fn query_with_vars<K, T, '_, '_>(&'_ Self, &'_ str, T) -> /*impl Trait*/\nwhere T: Serialize, K: for<'de> Deserialize","parent":null,"children":[],"decl_id":null,"docs":"","sig":null,"attributes":[]},{"kind":"Struct","id":{"krate":0,"index":217},"span":{"file_name":"/home/nick12345/.cargo/registry/src/github.com-1ecc6299db9ec823/gql_client-1.0.7/src/error.rs","byte_start":9592,"byte_end":9604,"line_start":8,"line_end":8,"column_start":12,"column_end":24},"name":"GraphQLError","qualname":"::error::GraphQLError","value":"GraphQLError {  }","parent":null,"children":[{"krate":0,"index":218},{"krate":0,"index":219}],"decl_id":null,"docs":"","sig":null,"attributes":[]},{"kind":"Struct","id":{"krate":0,"index":222},"span":{"file_name":"/home/nick12345/.cargo/registry/src/github.com-1ecc6299db9ec823/gql_client-1.0.7/src/error.rs","byte_start":9788,"byte_end":9807,"line_start":16,"line_end":16,"column_start":12,"column_end":31},"name":"GraphQLErrorMessage","qualname":"::error::GraphQLErrorMessage","value":"GraphQLErrorMessage {  }","parent":null,"children":[{"krate":0,"index":223},{"krate":0,"index":224},{"krate":0,"index":225},{"krate":0,"index":226}],"decl_id":null,"docs":"","sig":null,"attributes":[{"value":"allow(dead_code)","span":{"file_name":"/home/nick12345/.cargo/registry/src/github.com-1ecc6299db9ec823/gql_client-1.0.7/src/error.rs","byte_start":9757,"byte_end":9776,"line_start":15,"line_end":15,"column_start":1,"column_end":20}}]},{"kind":"Method","id":{"krate":0,"index":102},"span":{"file_name":"/home/nick12345/.cargo/registry/src/github.com-1ecc6299db9ec823/gql_client-1.0.7/src/error.rs","byte_start":10247,"byte_end":10256,"line_start":38,"line_end":38,"column_start":10,"column_end":19},"name":"with_text","qualname":"<GraphQLError>::with_text","value":"fn with_text<impl AsRef<str>>(impl AsRef<str>) -> Self where\nimpl AsRef<str>: AsRef<str>","parent":null,"children":[],"decl_id":null,"docs":"","sig":null,"attributes":[]},{"kind":"Method","id":{"krate":0,"index":104},"span":{"file_name":"/home/nick12345/.cargo/registry/src/github.com-1ecc6299db9ec823/gql_client-1.0.7/src/error.rs","byte_start":10387,"byte_end":10408,"line_start":45,"line_end":45,"column_start":10,"column_end":31},"name":"with_message_and_json","qualname":"<GraphQLError>::with_message_and_json","value":"fn with_message_and_json<impl AsRef<str>>(impl AsRef<str>,\nVec<GraphQLErrorMessage>) -> Self where impl AsRef<str>: AsRef<str>","parent":null,"children":[],"decl_id":null,"docs":"","sig":null,"attributes":[]},{"kind":"Method","id":{"krate":0,"index":106},"span":{"file_name":"/home/nick12345/.cargo/registry/src/github.com-1ecc6299db9ec823/gql_client-1.0.7/src/error.rs","byte_start":10577,"byte_end":10586,"line_start":52,"line_end":52,"column_start":10,"column_end":19},"name":"with_json","qualname":"<GraphQLError>::with_json","value":"fn with_json(Vec<GraphQLErrorMessage>) -> Self","parent":null,"children":[],"decl_id":null,"docs":"","sig":null,"attributes":[]},{"kind":"Method","id":{"krate":0,"index":107},"span":{"file_name":"/home/nick12345/.cargo/registry/src/github.com-1ecc6299db9ec823/gql_client-1.0.7/src/error.rs","byte_start":10720,"byte_end":10727,"line_start":56,"line_end":56,"column_start":10,"column_end":17},"name":"message","qualname":"<GraphQLError>::message","value":"fn message(&Self) -> &str","parent":null,"children":[],"decl_id":null,"docs":"","sig":null,"attributes":[]},{"kind":"Method","id":{"krate":0,"index":108},"span":{"file_name":"/home/nick12345/.cargo/registry/src/github.com-1ecc6299db9ec823/gql_client-1.0.7/src/error.rs","byte_start":10777,"byte_end":10781,"line_start":60,"line_end":60,"column_start":10,"column_end":14},"name":"json","qualname":"<GraphQLError>::json","value":"fn json(&Self) -> Option<Vec<GraphQLErrorMessage>>","parent":null,"children":[],"decl_id":null,"docs":"","sig":null,"attributes":[]},{"kind":"Method","id":{"krate":0,"index":111},"span":{"file_name":"/home/nick12345/.cargo/registry/src/github.com-1ecc6299db9ec823/gql_client-1.0.7/src/error.rs","byte_start":11282,"byte_end":11285,"line_start":84,"line_end":84,"column_start":6,"column_end":9},"name":"fmt","qualname":"<GraphQLError as std::fmt::Display>::fmt","value":"fn fmt(&Self, &mut Formatter) -> fmt::Result","parent":{"krate":2,"index":9907},"children":[],"decl_id":{"krate":2,"index":9908},"docs":"","sig":null,"attributes":[]},{"kind":"Method","id":{"krate":0,"index":113},"span":{"file_name":"/home/nick12345/.cargo/registry/src/github.com-1ecc6299db9ec823/gql_client-1.0.7/src/error.rs","byte_start":11436,"byte_end":11439,"line_start":91,"line_end":91,"column_start":6,"column_end":9},"name":"fmt","qualname":"<GraphQLError as std::fmt::Debug>::fmt","value":"fn fmt(&Self, &mut fmt::Formatter) -> fmt::Result","parent":{"krate":2,"index":9900},"children":[],"decl_id":{"krate":2,"index":9901},"docs":"","sig":null,"attributes":[{"value":"allow(clippy :: needless_borrow)","span":{"file_name":"/home/nick12345/.cargo/registry/src/github.com-1ecc6299db9ec823/gql_client-1.0.7/src/error.rs","byte_start":11397,"byte_end":11430,"line_start":90,"line_end":90,"column_start":3,"column_end":36}}]},{"kind":"Method","id":{"krate":0,"index":115},"span":{"file_name":"/home/nick12345/.cargo/registry/src/github.com-1ecc6299db9ec823/gql_client-1.0.7/src/error.rs","byte_start":11557,"byte_end":11561,"line_start":97,"line_end":97,"column_start":6,"column_end":10},"name":"from","qualname":"<GraphQLError as std::convert::From>::from","value":"fn from(Error) -> Self","parent":{"krate":2,"index":3056},"children":[],"decl_id":{"krate":2,"index":3058},"docs":"","sig":null,"attributes":[]},{"kind":"Struct","id":{"krate":0,"index":346},"span":{"file_name":"/home/nick12345/.cargo/registry/src/github.com-1ecc6299db9ec823/gql_client-1.0.7/src/types.rs","byte_start":11938,"byte_end":11950,"line_start":12,"line_end":12,"column_start":12,"column_end":24},"name":"ClientConfig","qualname":"::types::ClientConfig","value":"ClientConfig { endpoint, timeout, headers, proxy }","parent":null,"children":[{"krate":0,"index":347},{"krate":0,"index":348},{"krate":0,"index":349},{"krate":0,"index":350}],"decl_id":null,"docs":" GQL client config\n","sig":null,"attributes":[{"value":"/ GQL client config","span":{"file_name":"/home/nick12345/.cargo/registry/src/github.com-1ecc6299db9ec823/gql_client-1.0.7/src/types.rs","byte_start":11857,"byte_end":11878,"line_start":10,"line_end":10,"column_start":1,"column_end":22}}]},{"kind":"Field","id":{"krate":0,"index":347},"span":{"file_name":"/home/nick12345/.cargo/registry/src/github.com-1ecc6299db9ec823/gql_client-1.0.7/src/types.rs","byte_start":11999,"byte_end":12007,"line_start":14,"line_end":14,"column_start":7,"column_end":15},"name":"endpoint","qualname":"::types::ClientConfig::endpoint","value":"std::string::String","parent":{"krate":0,"index":346},"children":[],"decl_id":null,"docs":" the endpoint about graphql server\n","sig":null,"attributes":[{"value":"/ the endpoint about graphql server","span":{"file_name":"/home/nick12345/.cargo/registry/src/github.com-1ecc6299db9ec823/gql_client-1.0.7/src/types.rs","byte_start":11955,"byte_end":11992,"line_start":13,"line_end":13,"column_start":3,"column_end":40}}]},{"kind":"Field","id":{"krate":0,"index":348},"span":{"file_name":"/home/nick12345/.cargo/registry/src/github.com-1ecc6299db9ec823/gql_client-1.0.7/src/types.rs","byte_start":12062,"byte_end":12069,"line_start":16,"line_end":16,"column_start":7,"column_end":14},"name":"timeout","qualname":"::types::ClientConfig::timeout","value":"std::option::Option<u64>","parent":{"krate":0,"index":346},"children":[],"decl_id":null,"docs":" gql query timeout, unit: seconds\n","sig":null,"attributes":[{"value":"/ gql query timeout, unit: seconds","span":{"file_name":"/home/nick12345/.cargo/registry/src/github.com-1ecc6299db9ec823/gql_client-1.0.7/src/types.rs","byte_start":12019,"byte_end":12055,"line_start":15,"line_end":15,"column_start":3,"column_end":39}}]},{"kind":"Field","id":{"krate":0,"index":349},"span":{"file_name":"/home/nick12345/.cargo/registry/src/github.com-1ecc6299db9ec823/gql_client-1.0.7/src/types.rs","byte_start":12122,"byte_end":12129,"line_start":18,"line_end":18,"column_start":7,"column_end":14},"name":"headers","qualname":"::types::ClientConfig::headers","value":"std::option::Option<std::collections::HashMap<std::string::String, std::string::String>>","parent":{"krate":0,"index":346},"children":[],"decl_id":null,"docs":" additional request header\n","sig":null,"attributes":[{"value":"/ additional request header","span":{"file_name":"/home/nick12345/.cargo/registry/src/github.com-1ecc6299db9ec823/gql_client-1.0.7/src/types.rs","byte_start":12086,"byte_end":12115,"line_start":17,"line_end":17,"column_start":3,"column_end":32}}]},{"kind":"Field","id":{"krate":0,"index":350},"span":{"file_name":"/home/nick12345/.cargo/registry/src/github.com-1ecc6299db9ec823/gql_client-1.0.7/src/types.rs","byte_start":12190,"byte_end":12195,"line_start":20,"line_end":20,"column_start":7,"column_end":12},"name":"proxy","qualname":"::types::ClientConfig::proxy","value":"std::option::Option<types::GQLProxy>","parent":{"krate":0,"index":346},"children":[],"decl_id":null,"docs":" request proxy\n","sig":null,"attributes":[{"value":"/ request proxy","span":{"file_name":"/home/nick12345/.cargo/registry/src/github.com-1ecc6299db9ec823/gql_client-1.0.7/src/types.rs","byte_start":12166,"byte_end":12183,"line_start":19,"line_end":19,"column_start":3,"column_end":20}}]},{"kind":"TupleVariant","id":{"krate":0,"index":409},"span":{"file_name":"/home/nick12345/.cargo/registry/src/github.com-1ecc6299db9ec823/gql_client-1.0.7/src/types.rs","byte_start":12304,"byte_end":12308,"line_start":26,"line_end":26,"column_start":3,"column_end":7},"name":"Http","qualname":"::types::ProxyType::Http","value":"ProxyType::Http","parent":{"krate":0,"index":408},"children":[],"decl_id":null,"docs":"","sig":null,"attributes":[]},{"kind":"TupleVariant","id":{"krate":0,"index":411},"span":{"file_name":"/home/nick12345/.cargo/registry/src/github.com-1ecc6299db9ec823/gql_client-1.0.7/src/types.rs","byte_start":12312,"byte_end":12317,"line_start":27,"line_end":27,"column_start":3,"column_end":8},"name":"Https","qualname":"::types::ProxyType::Https","value":"ProxyType::Https","parent":{"krate":0,"index":408},"children":[],"decl_id":null,"docs":"","sig":null,"attributes":[]},{"kind":"TupleVariant","id":{"krate":0,"index":413},"span":{"file_name":"/home/nick12345/.cargo/registry/src/github.com-1ecc6299db9ec823/gql_client-1.0.7/src/types.rs","byte_start":12321,"byte_end":12324,"line_start":28,"line_end":28,"column_start":3,"column_end":6},"name":"All","qualname":"::types::ProxyType::All","value":"ProxyType::All","parent":{"krate":0,"index":408},"children":[],"decl_id":null,"docs":"","sig":null,"attributes":[]},{"kind":"Enum","id":{"krate":0,"index":408},"span":{"file_name":"/home/nick12345/.cargo/registry/src/github.com-1ecc6299db9ec823/gql_client-1.0.7/src/types.rs","byte_start":12290,"byte_end":12299,"line_start":25,"line_end":25,"column_start":10,"column_end":19},"name":"ProxyType","qualname":"::types::ProxyType","value":"enum ProxyType { Http, Https, All, }","parent":null,"children":[{"krate":0,"index":409},{"krate":0,"index":411},{"krate":0,"index":413}],"decl_id":null,"docs":" proxy type\n","sig":null,"attributes":[{"value":"/ proxy type","span":{"file_name":"/home/nick12345/.cargo/registry/src/github.com-1ecc6299db9ec823/gql_client-1.0.7/src/types.rs","byte_start":12218,"byte_end":12232,"line_start":23,"line_end":23,"column_start":1,"column_end":15}}]},{"kind":"Struct","id":{"krate":0,"index":466},"span":{"file_name":"/home/nick12345/.cargo/registry/src/github.com-1ecc6299db9ec823/gql_client-1.0.7/src/types.rs","byte_start":12415,"byte_end":12424,"line_start":33,"line_end":33,"column_start":12,"column_end":21},"name":"ProxyAuth","qualname":"::types::ProxyAuth","value":"ProxyAuth { username, password }","parent":null,"children":[{"krate":0,"index":467},{"krate":0,"index":468}],"decl_id":null,"docs":" proxy auth, basic_auth\n","sig":null,"attributes":[{"value":"/ proxy auth, basic_auth","span":{"file_name":"/home/nick12345/.cargo/registry/src/github.com-1ecc6299db9ec823/gql_client-1.0.7/src/types.rs","byte_start":12329,"byte_end":12355,"line_start":31,"line_end":31,"column_start":1,"column_end":27}}]},{"kind":"Field","id":{"krate":0,"index":467},"span":{"file_name":"/home/nick12345/.cargo/registry/src/github.com-1ecc6299db9ec823/gql_client-1.0.7/src/types.rs","byte_start":12433,"byte_end":12441,"line_start":34,"line_end":34,"column_start":7,"column_end":15},"name":"username","qualname":"::types::ProxyAuth::username","value":"std::string::String","parent":{"krate":0,"index":466},"children":[],"decl_id":null,"docs":"","sig":null,"attributes":[]},{"kind":"Field","id":{"krate":0,"index":468},"span":{"file_name":"/home/nick12345/.cargo/registry/src/github.com-1ecc6299db9ec823/gql_client-1.0.7/src/types.rs","byte_start":12457,"byte_end":12465,"line_start":35,"line_end":35,"column_start":7,"column_end":15},"name":"password","qualname":"::types::ProxyAuth::password","value":"std::string::String","parent":{"krate":0,"index":466},"children":[],"decl_id":null,"docs":"","sig":null,"attributes":[]},{"kind":"Struct","id":{"krate":0,"index":522},"span":{"file_name":"/home/nick12345/.cargo/registry/src/github.com-1ecc6299db9ec823/gql_client-1.0.7/src/types.rs","byte_start":12555,"byte_end":12563,"line_start":40,"line_end":40,"column_start":12,"column_end":20},"name":"GQLProxy","qualname":"::types::GQLProxy","value":"GQLProxy { schema, type_, auth }","parent":null,"children":[{"krate":0,"index":523},{"krate":0,"index":524},{"krate":0,"index":525}],"decl_id":null,"docs":" request proxy\n","sig":null,"attributes":[{"value":"/ request proxy","span":{"file_name":"/home/nick12345/.cargo/registry/src/github.com-1ecc6299db9ec823/gql_client-1.0.7/src/types.rs","byte_start":12478,"byte_end":12495,"line_start":38,"line_end":38,"column_start":1,"column_end":18}}]},{"kind":"Field","id":{"krate":0,"index":523},"span":{"file_name":"/home/nick12345/.cargo/registry/src/github.com-1ecc6299db9ec823/gql_client-1.0.7/src/types.rs","byte_start":12596,"byte_end":12602,"line_start":42,"line_end":42,"column_start":7,"column_end":13},"name":"schema","qualname":"::types::GQLProxy::schema","value":"std::string::String","parent":{"krate":0,"index":522},"children":[],"decl_id":null,"docs":" schema, proxy url\n","sig":null,"attributes":[{"value":"/ schema, proxy url","span":{"file_name":"/home/nick12345/.cargo/registry/src/github.com-1ecc6299db9ec823/gql_client-1.0.7/src/types.rs","byte_start":12568,"byte_end":12589,"line_start":41,"line_end":41,"column_start":3,"column_end":24}}]},{"kind":"Field","id":{"krate":0,"index":524},"span":{"file_name":"/home/nick12345/.cargo/registry/src/github.com-1ecc6299db9ec823/gql_client-1.0.7/src/types.rs","byte_start":12635,"byte_end":12640,"line_start":44,"line_end":44,"column_start":7,"column_end":12},"name":"type_","qualname":"::types::GQLProxy::type_","value":"types::ProxyType","parent":{"krate":0,"index":522},"children":[],"decl_id":null,"docs":" proxy type\n","sig":null,"attributes":[{"value":"/ proxy type","span":{"file_name":"/home/nick12345/.cargo/registry/src/github.com-1ecc6299db9ec823/gql_client-1.0.7/src/types.rs","byte_start":12614,"byte_end":12628,"line_start":43,"line_end":43,"column_start":3,"column_end":17}}]},{"kind":"Field","id":{"krate":0,"index":525},"span":{"file_name":"/home/nick12345/.cargo/registry/src/github.com-1ecc6299db9ec823/gql_client-1.0.7/src/types.rs","byte_start":12670,"byte_end":12674,"line_start":46,"line_end":46,"column_start":7,"column_end":11},"name":"auth","qualname":"::types::GQLProxy::auth","value":"std::option::Option<types::ProxyAuth>","parent":{"krate":0,"index":522},"children":[],"decl_id":null,"docs":" auth\n","sig":null,"attributes":[{"value":"/ auth","span":{"file_name":"/home/nick12345/.cargo/registry/src/github.com-1ecc6299db9ec823/gql_client-1.0.7/src/types.rs","byte_start":12655,"byte_end":12663,"line_start":45,"line_end":45,"column_start":3,"column_end":11}}]},{"kind":"Method","id":{"krate":0,"index":135},"span":{"file_name":"/home/nick12345/.cargo/registry/src/github.com-1ecc6299db9ec823/gql_client-1.0.7/src/types.rs","byte_start":12813,"byte_end":12821,"line_start":53,"line_end":53,"column_start":6,"column_end":14},"name":"try_from","qualname":"<reqwest::Proxy as std::convert::TryFrom>::try_from","value":"fn try_from(GQLProxy) -> Result<Self, Self::Error>","parent":{"krate":2,"index":3063},"children":[],"decl_id":{"krate":2,"index":3066},"docs":"","sig":null,"attributes":[]}],"impls":[{"id":2,"kind":"Inherent","span":{"file_name":"/home/nick12345/.cargo/registry/src/github.com-1ecc6299db9ec823/gql_client-1.0.7/src/client.rs","byte_start":3880,"byte_end":3889,"line_start":29,"line_end":29,"column_start":6,"column_end":15},"value":"","parent":null,"children":[{"krate":0,"index":38}],"docs":"","sig":null,"attributes":[]},{"id":3,"kind":"Inherent","span":{"file_name":"/home/nick12345/.cargo/registry/src/github.com-1ecc6299db9ec823/gql_client-1.0.7/src/client.rs","byte_start":4460,"byte_end":4469,"line_start":49,"line_end":49,"column_start":6,"column_end":15},"value":"","parent":null,"children":[{"krate":0,"index":41},{"krate":0,"index":43},{"krate":0,"index":48}],"docs":"","sig":null,"attributes":[]},{"id":4,"kind":"Inherent","span":{"file_name":"/home/nick12345/.cargo/registry/src/github.com-1ecc6299db9ec823/gql_client-1.0.7/src/client.rs","byte_start":5280,"byte_end":5289,"line_start":85,"line_end":85,"column_start":6,"column_end":15},"value":"","parent":null,"children":[{"krate":0,"index":50},{"krate":0,"index":55},{"krate":0,"index":60},{"krate":0,"index":66},{"krate":0,"index":72}],"docs":"","sig":null,"attributes":[]},{"id":8,"kind":"Inherent","span":{"file_name":"/home/nick12345/.cargo/registry/src/github.com-1ecc6299db9ec823/gql_client-1.0.7/src/error.rs","byte_start":10223,"byte_end":10235,"line_start":37,"line_end":37,"column_start":6,"column_end":18},"value":"","parent":null,"children":[{"krate":0,"index":102},{"krate":0,"index":104},{"krate":0,"index":106},{"krate":0,"index":107},{"krate":0,"index":108}],"docs":"","sig":null,"attributes":[]},{"id":9,"kind":"Direct","span":{"file_name":"/home/nick12345/.cargo/registry/src/github.com-1ecc6299db9ec823/gql_client-1.0.7/src/error.rs","byte_start":11262,"byte_end":11274,"line_start":83,"line_end":83,"column_start":23,"column_end":35},"value":"","parent":null,"children":[{"krate":0,"index":111}],"docs":"","sig":null,"attributes":[]},{"id":10,"kind":"Direct","span":{"file_name":"/home/nick12345/.cargo/registry/src/github.com-1ecc6299db9ec823/gql_client-1.0.7/src/error.rs","byte_start":11380,"byte_end":11392,"line_start":89,"line_end":89,"column_start":21,"column_end":33},"value":"","parent":null,"children":[{"krate":0,"index":113}],"docs":"","sig":null,"attributes":[]},{"id":11,"kind":"Direct","span":{"file_name":"/home/nick12345/.cargo/registry/src/github.com-1ecc6299db9ec823/gql_client-1.0.7/src/error.rs","byte_start":11537,"byte_end":11549,"line_start":96,"line_end":96,"column_start":22,"column_end":34},"value":"","parent":null,"children":[{"krate":0,"index":115}],"docs":"","sig":null,"attributes":[]},{"id":20,"kind":"Direct","span":{"file_name":"/home/nick12345/.cargo/registry/src/github.com-1ecc6299db9ec823/gql_client-1.0.7/src/types.rs","byte_start":12770,"byte_end":12775,"line_start":50,"line_end":50,"column_start":37,"column_end":42},"value":"","parent":null,"children":[{"krate":0,"index":134},{"krate":0,"index":135}],"docs":"","sig":null,"attributes":[]}],"refs":[],"macro_refs":[],"relations":[{"span":{"file_name":"/home/nick12345/.cargo/registry/src/github.com-1ecc6299db9ec823/gql_client-1.0.7/src/client.rs","byte_start":3880,"byte_end":3889,"line_start":29,"line_end":29,"column_start":6,"column_end":15},"kind":{"Impl":{"id":2}},"from":{"krate":0,"index":147},"to":{"krate":4294967295,"index":4294967295}},{"span":{"file_name":"/home/nick12345/.cargo/registry/src/github.com-1ecc6299db9ec823/gql_client-1.0.7/src/client.rs","byte_start":4460,"byte_end":4469,"line_start":49,"line_end":49,"column_start":6,"column_end":15},"kind":{"Impl":{"id":3}},"from":{"krate":0,"index":147},"to":{"krate":4294967295,"index":4294967295}},{"span":{"file_name":"/home/nick12345/.cargo/registry/src/github.com-1ecc6299db9ec823/gql_client-1.0.7/src/client.rs","byte_start":5280,"byte_end":5289,"line_start":85,"line_end":85,"column_start":6,"column_end":15},"kind":{"Impl":{"id":4}},"from":{"krate":0,"index":147},"to":{"krate":4294967295,"index":4294967295}},{"span":{"file_name":"/home/nick12345/.cargo/registry/src/github.com-1ecc6299db9ec823/gql_client-1.0.7/src/error.rs","byte_start":10223,"byte_end":10235,"line_start":37,"line_end":37,"column_start":6,"column_end":18},"kind":{"Impl":{"id":8}},"from":{"krate":0,"index":217},"to":{"krate":4294967295,"index":4294967295}},{"span":{"file_name":"/home/nick12345/.cargo/registry/src/github.com-1ecc6299db9ec823/gql_client-1.0.7/src/error.rs","byte_start":11262,"byte_end":11274,"line_start":83,"line_end":83,"column_start":23,"column_end":35},"kind":{"Impl":{"id":9}},"from":{"krate":0,"index":217},"to":{"krate":2,"index":9907}},{"span":{"file_name":"/home/nick12345/.cargo/registry/src/github.com-1ecc6299db9ec823/gql_client-1.0.7/src/error.rs","byte_start":11380,"byte_end":11392,"line_start":89,"line_end":89,"column_start":21,"column_end":33},"kind":{"Impl":{"id":10}},"from":{"krate":0,"index":217},"to":{"krate":2,"index":9900}},{"span":{"file_name":"/home/nick12345/.cargo/registry/src/github.com-1ecc6299db9ec823/gql_client-1.0.7/src/error.rs","byte_start":11537,"byte_end":11549,"line_start":96,"line_end":96,"column_start":22,"column_end":34},"kind":{"Impl":{"id":11}},"from":{"krate":0,"index":217},"to":{"krate":2,"index":3056}},{"span":{"file_name":"/home/nick12345/.cargo/registry/src/github.com-1ecc6299db9ec823/gql_client-1.0.7/src/types.rs","byte_start":12770,"byte_end":12775,"line_start":50,"line_end":50,"column_start":37,"column_end":42},"kind":{"Impl":{"id":20}},"from":{"krate":20,"index":1800},"to":{"krate":2,"index":3063}}]}